ahocorapy/__init__.py
ahocorapy/keywordtree.py
ahocorapy_visualizer/__init__.py
ahocorapy_visualizer/visualizer.py
ahocorapy-1.6.2.dist-info/LICENSE
ahocorapy-1.6.2.dist-info/METADATA
ahocorapy-1.6.2.dist-info/WHEEL
ahocorapy-1.6.2.dist-info/top_level.txt
ahocorapy-1.6.2.dist-info/RECORD
