Metadata-Version: 2.1
Name: ahocorapy
Version: 1.6.2
Summary: ahocorapy - Pure python ahocorasick implementation
Home-page: https://github.com/abusix/ahocorapy
Author: abusix
Author-email: fp@abusix.com
License: MIT
Project-URL: Source, https://github.com/abusix/ahocorapy
Project-URL: Company, https://www.abusix.com/
Keywords: keyword,search,purepython,aho-corasick,ahocorasick,abusix
Classifier: Development Status :: 5 - Production/Stable
Classifier: Intended Audience :: Developers
Classifier: Topic :: Software Development :: Libraries :: Python Modules
Classifier: License :: OSI Approved :: MIT License
Classifier: Programming Language :: Python :: 2
Classifier: Programming Language :: Python :: 2.7
Classifier: Programming Language :: Python :: 3
Classifier: Programming Language :: Python :: 3.3
Classifier: Programming Language :: Python :: 3.4
Classifier: Programming Language :: Python :: 3.5
Classifier: Programming Language :: Python :: 3.6
Classifier: Programming Language :: Python :: 3.7
Classifier: Programming Language :: Python :: 3.8
Classifier: Programming Language :: Python :: 3.9
Classifier: Programming Language :: Python :: 3.10
Classifier: Programming Language :: Python :: 3.11
Requires-Python: >=2.7
License-File: LICENSE
